deepcompare/__init__.py
python_deepcompare-2.1.0.dist-info/LICENSE
python_deepcompare-2.1.0.dist-info/METADATA
python_deepcompare-2.1.0.dist-info/WHEEL
python_deepcompare-2.1.0.dist-info/top_level.txt
python_deepcompare-2.1.0.dist-info/RECORD
