Metadata-Version: 2.1
Name: python-deepcompare
Version: 2.1.0
Summary: A library for deep comparison of data structures consisting of `dict`, `list` and `tuple`.
Home-page: https://github.com/anexia/python-deepcompare
Author: Andreas Stocker
Author-email: AStocker@anexia-it.com
License: MIT
Classifier: Development Status :: 5 - Production/Stable
Classifier: Intended Audience :: Developers
Classifier: License :: OSI Approved :: MIT License
Classifier: Operating System :: OS Independent
Classifier: Programming Language :: Python
Classifier: Programming Language :: Python :: 3
Classifier: Programming Language :: Python :: 3.9
Classifier: Programming Language :: Python :: 3.10
Classifier: Programming Language :: Python :: 3.11
Classifier: Programming Language :: Python :: 3.12
Classifier: Programming Language :: Python :: 3.13
Classifier: Topic :: Software Development
License-File: LICENSE
